protectionstnd-0.2.2.dist-info/METADATA
protectionstnd-0.2.2.dist-info/WHEEL
protectionstnd/__init__.py
protectionstnd/protectionstnd.cpython-310-x86_64-linux-gnu.so
protectionstnd-0.2.2.dist-info/RECORD
