Metadata-Version: 2.4
Name: protectionstnd
Version: 0.2.2
Classifier: Programming Language :: Rust
Classifier: Programming Language :: Python :: Implementation :: CPython
Classifier: Programming Language :: Python :: Implementation :: PyPy
Classifier: Operating System :: POSIX :: Linux
Classifier: Operating System :: Microsoft :: Windows
Classifier: Operating System :: MacOS
Requires-Dist: tomli>=1.1.0 ; python_full_version >= '3.10'
Summary: Security Protections, from sql injection to country specific protections
Author: Alejandro Martinez <aegloszenit@protonmail.com>
Author-email: Alejandro Martinez <aegloszenit@protonmail.com>
License: MIT OR Apache-2.0
Requires-Python: >=3.10
Project-URL: Source Code, https://github.com/zenitaeglos/protectionstnd.git
